{
  "schemaVersion": 1,
  "reportId": "01K00000000000000000000020",
  "generatedAtMs": 1760000004000,
  "manifest": [],
  "checks": [
    {
      "checkId": "storage.manifest.current_entries",
      "category": "storageManifest",
      "status": "passed",
      "severity": "info",
      "message": "Storage manifest covers all currently implemented stores.",
      "affectedPaths": [],
      "userAction": null,
      "details": "entries=16"
    },
    {
      "checkId": "workspace.registry.load_validate",
      "category": "workspaceRegistry",
      "status": "passed",
      "severity": "info",
      "message": "workspace-registry.json is readable and matches schema version.",
      "affectedPaths": ["/fixtures/app-data/workspace-registry.json"],
      "userAction": null,
      "details": null
    },
    {
      "checkId": "workspace.fallbacks.load_validate",
      "category": "workspaceFallbacks",
      "status": "passed",
      "severity": "info",
      "message": "workspace-fallbacks.json is readable and matches schema version.",
      "affectedPaths": ["/fixtures/app-data/workspace-fallbacks.json"],
      "userAction": null,
      "details": null
    },
    {
      "checkId": "settings.profile.load_validate",
      "category": "profileSettings",
      "status": "passed",
      "severity": "info",
      "message": "Profile settings are readable when initialized.",
      "affectedPaths": ["/fixtures/app-data/settings/profile.json"],
      "userAction": null,
      "details": null
    },
    {
      "checkId": "workspace.metadata.read_validate",
      "category": "workspaceMetadata",
      "status": "passed",
      "severity": "info",
      "message": ".orchlet/workspace.json is readable and matches schema version.",
      "affectedPaths": ["/fixtures/workspaces/alpha/.orchlet/workspace.json"],
      "userAction": null,
      "details": null
    },
    {
      "checkId": "member.profiles.schema_validate",
      "category": "memberProfiles",
      "status": "passed",
      "severity": "info",
      "message": "Member profile database is readable and has exactly one default owner.",
      "affectedPaths": ["/fixtures/app-data/workspaces/01K00000000000000000000000/orchlet.sqlite"],
      "userAction": null,
      "details": null
    },
    {
      "checkId": "contact.profiles.schema_validate",
      "category": "contactProfiles",
      "status": "passed",
      "severity": "info",
      "message": "Global contact store is readable when initialized.",
      "affectedPaths": ["/fixtures/app-data/global/orchlet.sqlite"],
      "userAction": null,
      "details": null
    },
    {
      "checkId": "conversation.records.schema_validate",
      "category": "conversationRecords",
      "status": "passed",
      "severity": "info",
      "message": "Conversation record store is readable when initialized.",
      "affectedPaths": ["/fixtures/app-data/workspaces/01K00000000000000000000000/orchlet.sqlite"],
      "userAction": null,
      "details": null
    },
    {
      "checkId": "conversation.members.schema_validate",
      "category": "conversationMembers",
      "status": "passed",
      "severity": "info",
      "message": "Conversation membership store is readable when initialized.",
      "affectedPaths": ["/fixtures/app-data/workspaces/01K00000000000000000000000/orchlet.sqlite"],
      "userAction": null,
      "details": null
    },
    {
      "checkId": "message.records.schema_validate",
      "category": "messageRecords",
      "status": "passed",
      "severity": "info",
      "message": "Message record store is readable when initialized.",
      "affectedPaths": ["/fixtures/app-data/workspaces/01K00000000000000000000000/orchlet.sqlite"],
      "userAction": null,
      "details": null
    },
    {
      "checkId": "message.mentions.schema_validate",
      "category": "messageMentions",
      "status": "passed",
      "severity": "info",
      "message": "Message mention store is readable when initialized.",
      "affectedPaths": ["/fixtures/app-data/workspaces/01K00000000000000000000000/orchlet.sqlite"],
      "userAction": null,
      "details": null
    },
    {
      "checkId": "conversation.read_positions.schema_validate",
      "category": "conversationReadPositions",
      "status": "passed",
      "severity": "info",
      "message": "Conversation read-position store is readable when initialized.",
      "affectedPaths": ["/fixtures/app-data/workspaces/01K00000000000000000000000/orchlet.sqlite"],
      "userAction": null,
      "details": null
    },
    {
      "checkId": "terminal.tabs.schema_validate",
      "category": "terminalTabs",
      "status": "passed",
      "severity": "info",
      "message": "Terminal tab store is readable when initialized.",
      "affectedPaths": ["/fixtures/app-data/workspaces/01K00000000000000000000000/orchlet.sqlite"],
      "userAction": null,
      "details": null
    },
    {
      "checkId": "skill.library.load_validate",
      "category": "skillLibrary",
      "status": "passed",
      "severity": "info",
      "message": "Skill library is readable when initialized.",
      "affectedPaths": ["/fixtures/app-data/skills/skill-library.json"],
      "userAction": null,
      "details": null
    },
    {
      "checkId": "skill.workspace_links.load_validate",
      "category": "workspaceSkillLinks",
      "status": "passed",
      "severity": "info",
      "message": "Workspace skill links are readable when initialized.",
      "affectedPaths": ["/fixtures/workspaces/alpha/.orchlet/skills/skill-links.json"],
      "userAction": null,
      "details": null
    },
    {
      "checkId": "roadmap.tasks.load_validate",
      "category": "roadmapTasks",
      "status": "passed",
      "severity": "info",
      "message": "Roadmap tasks are readable when initialized.",
      "affectedPaths": ["/fixtures/workspaces/alpha/.orchlet/roadmap/tasks.json"],
      "userAction": null,
      "details": null
    },
    {
      "checkId": "roadmap.goals.load_validate",
      "category": "roadmapGoals",
      "status": "passed",
      "severity": "info",
      "message": "Roadmap goals are readable when initialized.",
      "affectedPaths": ["/fixtures/workspaces/alpha/.orchlet/roadmap/goals.json"],
      "userAction": null,
      "details": null
    }
  ],
  "totalChecks": 17,
  "passedChecks": 17,
  "failedChecks": 0,
  "skippedChecks": 0,
  "hasFailures": false,
  "batched": true
}
